[
  {
    "digest_date": "2026-07-01",
    "timezone": "Asia/Shanghai",
    "article_count": 4,
    "company_count": 4,
    "event_counts": {
      "other": 1,
      "macro_market": 1,
      "operations_product": 1,
      "governance_personnel": 1
    },
    "sentiment_counts": {
      "neutral": 2,
      "negative": 1,
      "positive": 1
    },
    "payload": {
      "synthetic": true,
      "not_investment_advice": true,
      "groups": [
        {
          "article_id": "03047894-477c-40c2-bbe3-5df7105c11ce",
          "title": "MetroSeed Foods publishes routine investor calendar update",
          "source": "Synthetic Local Feed",
          "url": "https://demo.local/synthetic-evening-brief/mtr-103?id=103",
          "event": "other",
          "sentiment": "neutral",
          "company_ids": [
            "ce6fe592-0301-4857-a9f7-baaa14f3104a"
          ]
        },
        {
          "article_id": "8bedbf32-1172-4789-8f69-1c9945231634",
          "title": "PrimeVale notes softer macro market orders",
          "source": "Synthetic Local Feed",
          "url": "https://demo.local/synthetic-jsonl-desk/prm-104?id=104",
          "event": "macro_market",
          "sentiment": "negative",
          "company_ids": [
            "711b51ee-7ced-4000-8fd8-5b414c94ba43"
          ]
        },
        {
          "article_id": "d8060521-b5c6-432a-af4a-a477aaad60fb",
          "title": "阿尔派机器人推出区域客户维护平台",
          "source": "Synthetic Local Feed",
          "url": "https://demo.local/synthetic-import-wire/alp-101?id=101",
          "event": "operations_product",
          "sentiment": "positive",
          "company_ids": [
            "92ff5c41-9325-4c0d-8a59-d31816428f63"
          ]
        },
        {
          "article_id": "5008d599-f78f-4ab0-a2f2-5f670da0aa1a",
          "title": "QuantHarbor appoints new chief operating officer",
          "source": "Synthetic Local Feed",
          "url": "https://demo.local/synthetic-announcement-board/qnt-102?id=102",
          "event": "governance_personnel",
          "sentiment": "neutral",
          "company_ids": [
            "580c0712-bfbd-4648-b77d-ff94c2c10bb9"
          ]
        }
      ]
    }
  },
  {
    "digest_date": "2026-06-23",
    "timezone": "Asia/Shanghai",
    "article_count": 7,
    "company_count": 7,
    "event_counts": {
      "financing_capital": 1,
      "policy_regulation": 1,
      "litigation_penalty": 1,
      "operations_product": 1,
      "earnings": 1,
      "macro_market": 1,
      "merger_acquisition": 1
    },
    "sentiment_counts": {
      "uncertain": 2,
      "neutral": 1,
      "negative": 2,
      "positive": 2
    },
    "payload": {
      "synthetic": true,
      "not_investment_advice": true,
      "groups": [
        {
          "article_id": "08e6f02f-7a7d-4c3a-97f0-59177c4506ff",
          "title": "量港分析披露扩产融资计划",
          "source": "Synthetic Import Wire",
          "url": "https://demo.local/synthetic-import-wire/qnt-041?id=41",
          "event": "financing_capital",
          "sentiment": "uncertain",
          "company_ids": [
            "580c0712-bfbd-4648-b77d-ff94c2c10bb9"
          ]
        },
        {
          "article_id": "768d3c1e-53f1-4e67-ba0d-d9702408f264",
          "title": "HelioStorage responds to new sector policy guidance",
          "source": "Synthetic Evening Brief",
          "url": "https://demo.local/synthetic-evening-brief/hls-039?id=39",
          "event": "policy_regulation",
          "sentiment": "neutral",
          "company_ids": [
            "9cec562c-d156-4060-8312-743b8bd3e33f"
          ]
        },
        {
          "article_id": "243cb893-e2f5-473b-8c65-2a31855c34b4",
          "title": "AOrchid Circuit warns about overseas litigation expense pressure",
          "source": "Synthetic Announcement Board",
          "url": "https://demo.local/synthetic-announcement-board/orc-042?id=42",
          "event": "litigation_penalty",
          "sentiment": "negative",
          "company_ids": [
            "1e40ed36-943e-458d-8618-a7e0dcd3d1d1"
          ]
        },
        {
          "article_id": "6f22be7e-2da4-4ffc-bbc1-c6066cda9719",
          "title": "NovaMed launches maintenance platform for regional customers",
          "source": "Synthetic JSONL Desk",
          "url": "https://demo.local/synthetic-jsonl-desk/nvm-040?id=40",
          "event": "operations_product",
          "sentiment": "positive",
          "company_ids": [
            "e5afe6da-01cc-430e-9d77-760cf1940fc6"
          ]
        },
        {
          "article_id": "a5ef5ee0-3a40-4ced-9feb-8b6598326ddb",
          "title": "Alpine Robotics reports higher quarterly earnings after service demand improved",
          "source": "Synthetic Import Wire",
          "url": "https://demo.local/synthetic-import-wire/alp-037?id=37",
          "event": "earnings",
          "sentiment": "positive",
          "company_ids": [
            "92ff5c41-9325-4c0d-8a59-d31816428f63"
          ]
        },
        {
          "article_id": "6ff7c4e1-5164-48af-9b23-d5afb5b07329",
          "title": "A启谷物流提示宏观市场订单偏弱",
          "source": "Synthetic Evening Brief",
          "url": "https://demo.local/synthetic-evening-brief/prm-035?id=35",
          "event": "macro_market",
          "sentiment": "negative",
          "company_ids": [
            "711b51ee-7ced-4000-8fd8-5b414c94ba43"
          ]
        },
        {
          "article_id": "fba89a88-7596-4c73-9ed3-2c09296a2de0",
          "title": "明河云签署非约束性并购讨论备忘录",
          "source": "Synthetic Announcement Board",
          "url": "https://demo.local/synthetic-announcement-board/brc-038?id=38",
          "event": "merger_acquisition",
          "sentiment": "uncertain",
          "company_ids": [
            "8aa42885-c947-4695-afaf-38e8775be1c8"
          ]
        }
      ]
    }
  },
  {
    "digest_date": "2026-06-22",
    "timezone": "Asia/Shanghai",
    "article_count": 8,
    "company_count": 8,
    "event_counts": {
      "other": 2,
      "litigation_penalty": 1,
      "operations_product": 1,
      "governance_personnel": 1,
      "financing_capital": 1,
      "merger_acquisition": 1,
      "policy_regulation": 1
    },
    "sentiment_counts": {
      "neutral": 4,
      "negative": 1,
      "positive": 1,
      "uncertain": 2
    },
    "payload": {
      "synthetic": true,
      "not_investment_advice": true,
      "groups": [
        {
          "article_id": "578decce-ecfa-4fc8-805d-2a3c53d2a348",
          "title": "EcoMosaic publishes routine investor calendar update",
          "source": "Synthetic JSONL Desk",
          "url": "https://demo.local/synthetic-jsonl-desk/eco-036?id=36",
          "event": "other",
          "sentiment": "neutral",
          "company_ids": [
            "284f7ca6-1b4d-4a45-8aae-0b71f90e2a1e"
          ]
        },
        {
          "article_id": "07add865-9c41-43f0-b65d-a860c391405b",
          "title": "SkyForge warns about overseas litigation expense pressure",
          "source": "Synthetic Import Wire",
          "url": "https://demo.local/synthetic-import-wire/sky-033?id=33",
          "event": "litigation_penalty",
          "sentiment": "negative",
          "company_ids": [
            "4966bce3-2120-4f01-9dd5-bad9490d01bb"
          ]
        },
        {
          "article_id": "7929174c-935c-43a9-ae37-389c8f3b1e66",
          "title": "VectorLoom launches maintenance platform for regional customers",
          "source": "Synthetic Evening Brief",
          "url": "https://demo.local/synthetic-evening-brief/vtl-031?id=31",
          "event": "operations_product",
          "sentiment": "positive",
          "company_ids": [
            "6bbaad9d-d481-4708-8951-e2a46737253e"
          ]
        },
        {
          "article_id": "9844a135-6e70-4163-b587-942d6561eb29",
          "title": "LumenBridge appoints new chief operating officer",
          "source": "Synthetic Announcement Board",
          "url": "https://demo.local/synthetic-announcement-board/lum-034?id=34",
          "event": "governance_personnel",
          "sentiment": "neutral",
          "company_ids": [
            "00df5df4-6429-4834-b9dc-be7606a8bdad"
          ]
        },
        {
          "article_id": "16e2ed35-7de0-4f24-91f3-79ea1bec14c8",
          "title": "城籽食品披露扩产融资计划",
          "source": "Synthetic JSONL Desk",
          "url": "https://demo.local/synthetic-jsonl-desk/mtr-032?id=32",
          "event": "financing_capital",
          "sentiment": "uncertain",
          "company_ids": [
            "ce6fe592-0301-4857-a9f7-baaa14f3104a"
          ]
        },
        {
          "article_id": "e837285e-5947-47ef-8640-0a12c07182b9",
          "title": "量港分析签署非约束性并购讨论备忘录",
          "source": "Synthetic Import Wire",
          "url": "https://demo.local/synthetic-import-wire/qnt-029?id=29",
          "event": "merger_acquisition",
          "sentiment": "uncertain",
          "company_ids": [
            "580c0712-bfbd-4648-b77d-ff94c2c10bb9"
          ]
        },
        {
          "article_id": "c685c3a8-3852-4318-863a-86967a2b1715",
          "title": "HelioStorage publishes routine investor calendar update",
          "source": "Synthetic Evening Brief",
          "url": "https://demo.local/synthetic-evening-brief/hls-027?id=27",
          "event": "other",
          "sentiment": "neutral",
          "company_ids": [
            "9cec562c-d156-4060-8312-743b8bd3e33f"
          ]
        },
        {
          "article_id": "99c3e60f-c8b0-46bd-9e06-f13bc867577c",
          "title": "Orchid Circuit responds to new sector policy guidance",
          "source": "Synthetic Announcement Board",
          "url": "https://demo.local/synthetic-announcement-board/orc-030?id=30",
          "event": "policy_regulation",
          "sentiment": "neutral",
          "company_ids": [
            "1e40ed36-943e-458d-8618-a7e0dcd3d1d1"
          ]
        }
      ]
    }
  },
  {
    "digest_date": "2026-06-21",
    "timezone": "Asia/Shanghai",
    "article_count": 8,
    "company_count": 8,
    "event_counts": {
      "earnings": 2,
      "governance_personnel": 1,
      "financing_capital": 1,
      "macro_market": 1,
      "litigation_penalty": 1,
      "policy_regulation": 1,
      "operations_product": 1
    },
    "sentiment_counts": {
      "positive": 3,
      "neutral": 2,
      "uncertain": 1,
      "negative": 2
    },
    "payload": {
      "synthetic": true,
      "not_investment_advice": true,
      "groups": [
        {
          "article_id": "4034e219-b0b2-4076-adc9-7d6003df0f67",
          "title": "ANovaMed reports higher quarterly earnings after service demand improved",
          "source": "Synthetic JSONL Desk",
          "url": "https://demo.local/synthetic-jsonl-desk/nvm-028?id=28",
          "event": "earnings",
          "sentiment": "positive",
          "company_ids": [
            "e5afe6da-01cc-430e-9d77-760cf1940fc6"
          ]
        },
        {
          "article_id": "4ef1380e-8c19-4c85-b557-6cf5d1dc7293",
          "title": "Alpine Robotics appoints new chief operating officer",
          "source": "Synthetic Import Wire",
          "url": "https://demo.local/synthetic-import-wire/alp-025?id=25",
          "event": "governance_personnel",
          "sentiment": "neutral",
          "company_ids": [
            "92ff5c41-9325-4c0d-8a59-d31816428f63"
          ]
        },
        {
          "article_id": "44f95c97-e933-4958-ad31-1a542c28e1d3",
          "title": "启谷物流披露扩产融资计划",
          "source": "Synthetic Evening Brief",
          "url": "https://demo.local/synthetic-evening-brief/prm-023?id=23",
          "event": "financing_capital",
          "sentiment": "uncertain",
          "company_ids": [
            "711b51ee-7ced-4000-8fd8-5b414c94ba43"
          ]
        },
        {
          "article_id": "c6ac32eb-b271-4ae7-b2cd-32a3753c7fcc",
          "title": "明河云提示宏观市场订单偏弱",
          "source": "Synthetic Announcement Board",
          "url": "https://demo.local/synthetic-announcement-board/brc-026?id=26",
          "event": "macro_market",
          "sentiment": "negative",
          "company_ids": [
            "8aa42885-c947-4695-afaf-38e8775be1c8"
          ]
        },
        {
          "article_id": "5f2e4712-8065-4023-ad6b-59f881b78254",
          "title": "EcoMosaic warns about overseas litigation expense pressure",
          "source": "Synthetic JSONL Desk",
          "url": "https://demo.local/synthetic-jsonl-desk/eco-024?id=24",
          "event": "litigation_penalty",
          "sentiment": "negative",
          "company_ids": [
            "284f7ca6-1b4d-4a45-8aae-0b71f90e2a1e"
          ]
        },
        {
          "article_id": "3d1fd5b9-6ef2-4a6d-bb6e-01b55eb4ecb2",
          "title": "ASkyForge responds to new sector policy guidance",
          "source": "Synthetic Import Wire",
          "url": "https://demo.local/synthetic-import-wire/sky-021?id=21",
          "event": "policy_regulation",
          "sentiment": "neutral",
          "company_ids": [
            "4966bce3-2120-4f01-9dd5-bad9490d01bb"
          ]
        },
        {
          "article_id": "e568df94-e6c6-4dad-a2bf-665d2cc971e4",
          "title": "VectorLoom reports higher quarterly earnings after service demand improved",
          "source": "Synthetic Evening Brief",
          "url": "https://demo.local/synthetic-evening-brief/vtl-019?id=19",
          "event": "earnings",
          "sentiment": "positive",
          "company_ids": [
            "6bbaad9d-d481-4708-8951-e2a46737253e"
          ]
        },
        {
          "article_id": "a47a4438-bc1e-41ef-8c40-16de0c090269",
          "title": "LumenBridge launches maintenance platform for regional customers",
          "source": "Synthetic Announcement Board",
          "url": "https://demo.local/synthetic-announcement-board/lum-022?id=22",
          "event": "operations_product",
          "sentiment": "positive",
          "company_ids": [
            "00df5df4-6429-4834-b9dc-be7606a8bdad"
          ]
        }
      ]
    }
  },
  {
    "digest_date": "2026-06-20",
    "timezone": "Asia/Shanghai",
    "article_count": 8,
    "company_count": 8,
    "event_counts": {
      "merger_acquisition": 2,
      "macro_market": 1,
      "litigation_penalty": 1,
      "other": 1,
      "governance_personnel": 1,
      "operations_product": 1,
      "financing_capital": 1
    },
    "sentiment_counts": {
      "uncertain": 3,
      "negative": 2,
      "neutral": 2,
      "positive": 1
    },
    "payload": {
      "synthetic": true,
      "not_investment_advice": true,
      "groups": [
        {
          "article_id": "e0b8abbf-4e0e-4b8e-9d8e-aaac095a8fb4",
          "title": "城籽食品签署非约束性并购讨论备忘录",
          "source": "Synthetic JSONL Desk",
          "url": "https://demo.local/synthetic-jsonl-desk/mtr-020?id=20",
          "event": "merger_acquisition",
          "sentiment": "uncertain",
          "company_ids": [
            "ce6fe592-0301-4857-a9f7-baaa14f3104a"
          ]
        },
        {
          "article_id": "c13273cf-1b5f-4918-9666-ae380cdb2665",
          "title": "量港分析提示宏观市场订单偏弱",
          "source": "Synthetic Import Wire",
          "url": "https://demo.local/synthetic-import-wire/qnt-017?id=17",
          "event": "macro_market",
          "sentiment": "negative",
          "company_ids": [
            "580c0712-bfbd-4648-b77d-ff94c2c10bb9"
          ]
        },
        {
          "article_id": "56eae367-6f55-473e-b487-e4e9babae64c",
          "title": "HelioStorage warns about overseas litigation expense pressure",
          "source": "Synthetic Evening Brief",
          "url": "https://demo.local/synthetic-evening-brief/hls-015?id=15",
          "event": "litigation_penalty",
          "sentiment": "negative",
          "company_ids": [
            "9cec562c-d156-4060-8312-743b8bd3e33f"
          ]
        },
        {
          "article_id": "d4ef75c7-496b-4caa-8d47-fbfb9457a686",
          "title": "Orchid Circuit publishes routine investor calendar update",
          "source": "Synthetic Announcement Board",
          "url": "https://demo.local/synthetic-announcement-board/orc-018?id=18",
          "event": "other",
          "sentiment": "neutral",
          "company_ids": [
            "1e40ed36-943e-458d-8618-a7e0dcd3d1d1"
          ]
        },
        {
          "article_id": "86c20fbe-d133-45ac-a3bf-bcb007114adc",
          "title": "NovaMed appoints new chief operating officer",
          "source": "Synthetic JSONL Desk",
          "url": "https://demo.local/synthetic-jsonl-desk/nvm-016?id=16",
          "event": "governance_personnel",
          "sentiment": "neutral",
          "company_ids": [
            "e5afe6da-01cc-430e-9d77-760cf1940fc6"
          ]
        },
        {
          "article_id": "a107fcdc-6472-4ba3-80a3-4650a15732af",
          "title": "Alpine Robotics launches maintenance platform for regional customers",
          "source": "Synthetic Import Wire",
          "url": "https://demo.local/synthetic-import-wire/alp-013?id=13",
          "event": "operations_product",
          "sentiment": "positive",
          "company_ids": [
            "92ff5c41-9325-4c0d-8a59-d31816428f63"
          ]
        },
        {
          "article_id": "c105c691-8a5d-49ef-b597-0e5f8d99a3ec",
          "title": "启谷物流签署非约束性并购讨论备忘录",
          "source": "Synthetic Evening Brief",
          "url": "https://demo.local/synthetic-evening-brief/prm-011?id=11",
          "event": "merger_acquisition",
          "sentiment": "uncertain",
          "company_ids": [
            "711b51ee-7ced-4000-8fd8-5b414c94ba43"
          ]
        },
        {
          "article_id": "ee63b7f9-7c18-46d6-b5f5-b235e11dfcfa",
          "title": "A明河云披露扩产融资计划",
          "source": "Synthetic Announcement Board",
          "url": "https://demo.local/synthetic-announcement-board/brc-014?id=14",
          "event": "financing_capital",
          "sentiment": "uncertain",
          "company_ids": [
            "8aa42885-c947-4695-afaf-38e8775be1c8"
          ]
        }
      ]
    }
  },
  {
    "digest_date": "2026-06-19",
    "timezone": "Asia/Shanghai",
    "article_count": 8,
    "company_count": 8,
    "event_counts": {
      "policy_regulation": 2,
      "other": 1,
      "governance_personnel": 1,
      "earnings": 1,
      "macro_market": 1,
      "financing_capital": 1,
      "litigation_penalty": 1
    },
    "sentiment_counts": {
      "neutral": 4,
      "positive": 1,
      "negative": 2,
      "uncertain": 1
    },
    "payload": {
      "synthetic": true,
      "not_investment_advice": true,
      "groups": [
        {
          "article_id": "e9da21dc-4fb6-4d30-8f50-1f6431e0b35a",
          "title": "EcoMosaic responds to new sector policy guidance",
          "source": "Synthetic JSONL Desk",
          "url": "https://demo.local/synthetic-jsonl-desk/eco-012?id=12",
          "event": "policy_regulation",
          "sentiment": "neutral",
          "company_ids": [
            "284f7ca6-1b4d-4a45-8aae-0b71f90e2a1e"
          ]
        },
        {
          "article_id": "9092ebd5-1a4a-4404-81be-a0b1b80be7b6",
          "title": "SkyForge publishes routine investor calendar update",
          "source": "Synthetic Import Wire",
          "url": "https://demo.local/synthetic-import-wire/sky-009?id=9",
          "event": "other",
          "sentiment": "neutral",
          "company_ids": [
            "4966bce3-2120-4f01-9dd5-bad9490d01bb"
          ]
        },
        {
          "article_id": "3b74a352-1479-4511-9d73-5cf07948ccd3",
          "title": "AVectorLoom appoints new chief operating officer",
          "source": "Synthetic Evening Brief",
          "url": "https://demo.local/synthetic-evening-brief/vtl-007?id=7",
          "event": "governance_personnel",
          "sentiment": "neutral",
          "company_ids": [
            "6bbaad9d-d481-4708-8951-e2a46737253e"
          ]
        },
        {
          "article_id": "5782575d-4655-4864-bb7a-59f849c9b234",
          "title": "LumenBridge reports higher quarterly earnings after service demand improved",
          "source": "Synthetic Announcement Board",
          "url": "https://demo.local/synthetic-announcement-board/lum-010?id=10",
          "event": "earnings",
          "sentiment": "positive",
          "company_ids": [
            "00df5df4-6429-4834-b9dc-be7606a8bdad"
          ]
        },
        {
          "article_id": "274ad142-c51f-4778-8f67-035469b4302f",
          "title": "城籽食品提示宏观市场订单偏弱",
          "source": "Synthetic JSONL Desk",
          "url": "https://demo.local/synthetic-jsonl-desk/mtr-008?id=8",
          "event": "macro_market",
          "sentiment": "negative",
          "company_ids": [
            "ce6fe592-0301-4857-a9f7-baaa14f3104a"
          ]
        },
        {
          "article_id": "ecba19ed-1c7b-4731-9a41-5237f812dbb5",
          "title": "量港分析披露扩产融资计划",
          "source": "Synthetic Import Wire",
          "url": "https://demo.local/synthetic-import-wire/qnt-005?id=5",
          "event": "financing_capital",
          "sentiment": "uncertain",
          "company_ids": [
            "580c0712-bfbd-4648-b77d-ff94c2c10bb9"
          ]
        },
        {
          "article_id": "c6b39d03-e408-4b6a-afc3-79745ce6b2a0",
          "title": "HelioStorage responds to new sector policy guidance",
          "source": "Synthetic Evening Brief",
          "url": "https://demo.local/synthetic-evening-brief/hls-003?id=3",
          "event": "policy_regulation",
          "sentiment": "neutral",
          "company_ids": [
            "9cec562c-d156-4060-8312-743b8bd3e33f"
          ]
        },
        {
          "article_id": "84b3dda0-26a7-45b9-8d2c-41786090d97e",
          "title": "Orchid Circuit warns about overseas litigation expense pressure",
          "source": "Synthetic Announcement Board",
          "url": "https://demo.local/synthetic-announcement-board/orc-006?id=6",
          "event": "litigation_penalty",
          "sentiment": "negative",
          "company_ids": [
            "1e40ed36-943e-458d-8618-a7e0dcd3d1d1"
          ]
        }
      ]
    }
  },
  {
    "digest_date": "2026-06-18",
    "timezone": "Asia/Shanghai",
    "article_count": 3,
    "company_count": 3,
    "event_counts": {
      "operations_product": 1,
      "earnings": 1,
      "merger_acquisition": 1
    },
    "sentiment_counts": {
      "positive": 2,
      "uncertain": 1
    },
    "payload": {
      "synthetic": true,
      "not_investment_advice": true,
      "groups": [
        {
          "article_id": "dd99d5ca-afa9-4949-8ec8-2c1e3682ce98",
          "title": "NovaMed launches maintenance platform for regional customers",
          "source": "Synthetic JSONL Desk",
          "url": "https://demo.local/synthetic-jsonl-desk/nvm-004?id=4",
          "event": "operations_product",
          "sentiment": "positive",
          "company_ids": [
            "e5afe6da-01cc-430e-9d77-760cf1940fc6"
          ]
        },
        {
          "article_id": "76964a00-2e79-45e0-9c28-574844999dc4",
          "title": "Alpine Robotics reports higher quarterly earnings after service demand improved",
          "source": "Synthetic Import Wire",
          "url": "https://demo.local/synthetic-import-wire/alp-001?id=1",
          "event": "earnings",
          "sentiment": "positive",
          "company_ids": [
            "92ff5c41-9325-4c0d-8a59-d31816428f63"
          ]
        },
        {
          "article_id": "9a8df50a-89af-4405-b49d-31083cabafac",
          "title": "明河云签署非约束性并购讨论备忘录",
          "source": "Synthetic Announcement Board",
          "url": "https://demo.local/synthetic-announcement-board/brc-002?id=2",
          "event": "merger_acquisition",
          "sentiment": "uncertain",
          "company_ids": [
            "8aa42885-c947-4695-afaf-38e8775be1c8"
          ]
        }
      ]
    }
  }
]